setup.py
django_yadt/__init__.py
django_yadt/fields.py
django_yadt/models.py
django_yadt/processors.py
django_yadt/utils.py
django_yadt.egg-info/PKG-INFO
django_yadt.egg-info/SOURCES.txt
django_yadt.egg-info/dependency_links.txt
django_yadt.egg-info/requires.txt
django_yadt.egg-info/top_level.txt
django_yadt/management/__init__.py
django_yadt/management/commands/__init__.py
django_yadt/management/commands/yadt_gc.py
django_yadt/management/commands/yadt_generate_fallback_config.py
django_yadt/management/commands/yadt_invalidate_variant.py
django_yadt/management/commands/yadt_refresh_variant.py