Metadata-Version: 1.0
Name: django-yadt
Version: 2.0.5
Summary: Yet Another Django Thumbnailer
Home-page: https://chris-lamb.co.uk/projects/django-yadt
Author: Chris Lamb
Author-email: chris@chris-lamb.co.uk
License: BSD
Platform: UNKNOWN
